factorial_minhbao/__init__.py
factorial_minhbao/app.py
factorial_minhbao/factorial.py
factorial_minhbao-0.1.0.dist-info/METADATA
factorial_minhbao-0.1.0.dist-info/WHEEL
factorial_minhbao-0.1.0.dist-info/RECORD
