Metadata-Version: 2.1
Name: factorial-minhbao
Version: 0.1.0
Summary: 
Author: minhbao1705
Author-email: vo.minhbao9406@gmail.com
Requires-Python: >=3.12,<4.0
Classifier: Programming Language :: Python :: 3
Classifier: Programming Language :: Python :: 3.12
Requires-Dist: streamlit (>=1.33.0,<2.0.0)
